{
  "file_name": "VCS_1465_1.pdf",
  "chunk_index": 30,
  "page": 16,
  "content": "As mentioned in the VCS Project Description, the calibration is not within the control of project proponent as it is the responsibility of respective state DISCOM. It is also the minimum requirement as per host country rules based on the Central Electricity Authority (CEA) notification on 17-March-2006, that the calibration of the billing meters is atleast once in 5 years. Hence as no clear frequency was established by the state monitoring agencies, using the criteria as per CEA regulations, the calibration validity was assessed and the requirements were fulfilled as per information indicated below:\n\n16\n\n: VERIFIED \\ CARBSN STANDARD\n\nVERIFICATION REPORT: ves Version 3\n\nThe calibration details of the project energy meters are as follows:\n\nOJWEPL\n\nMeter Meter Accuracy 1* calibration 2\" Calibration* Number class Calibration Calibration | Calibration | Calibration date due date date due date GSS _ Main | RJB80790 | 0.2s 29-March- 28-March- | 13-Jan- 12-Jan- Meter 2013 2018 2015 2020 GSS RJB80791 | 0.2s 29-March- 28-March- | 13-Jan- 12-Jan- Check 2013 2018 2015 2020 Meter PSS Main 0.2s 29-March- 28-March- | 13-Jan- 12-Jan- Meter 1 RIB78198 2013 2018 2015 2020 PSS Check RIB78200 0.2s 29-March- 28-March- | 13-Jan- 12-Jan- meter 1 2013 2018 2015 2020 PSS Main 0.2s 29-March- 28-March- | 13-Jan- 12-Jan- Meter 2 RIB78201 2013 2018 2015 2020 PSS Check 0.2s 29-March- 28-March- | 13-Jan- 12-Jan- meter 2 RIB78203 2013 2018 2015 2020",
  "entities": {
    "CAR": [],
    "CL": [],
    "FAR": []
  },
  "content_length": 1441,
  "processed_date": "2025-08-07T19:36:24.952977"
}